t64/__init__.py
t64/dir_entry.py
t64/magic.py
t64/t64_image_reader.py
t64-1.2.dist-info/LICENSE
t64-1.2.dist-info/METADATA
t64-1.2.dist-info/WHEEL
t64-1.2.dist-info/top_level.txt
t64-1.2.dist-info/RECORD
