Metadata-Version: 2.1
Name: t64
Version: 1.2
Summary: Read Commodore tape container images
Home-page: https://eden.mose.org.uk/gitweb/?p=python-t64.git
Author: Simon Rowe
Author-email: srowe@mose.org.uk
License: UNKNOWN
Platform: UNKNOWN
Classifier: Development Status :: 5 - Production/Stable
Classifier: Intended Audience :: Developers
Classifier: License :: OSI Approved :: GNU General Public License v2 (GPLv2)
Classifier: Programming Language :: Python
Classifier: Programming Language :: Python :: 3
Classifier: Topic :: Software Development :: Libraries :: Python Modules
